dungeons_and_trolls_client/__init__.py
dungeons_and_trolls_client/api_client.py
dungeons_and_trolls_client/api_response.py
dungeons_and_trolls_client/configuration.py
dungeons_and_trolls_client/exceptions.py
dungeons_and_trolls_client/py.typed
dungeons_and_trolls_client/rest.py
dungeons_and_trolls_client/api/__init__.py
dungeons_and_trolls_client/api/dungeons_and_trolls_api.py
dungeons_and_trolls_client/models/__init__.py
dungeons_and_trolls_client/models/dungeonsandtrolls_attributes.py
dungeons_and_trolls_client/models/dungeonsandtrolls_available_levels.py
dungeons_and_trolls_client/models/dungeonsandtrolls_character.py
dungeons_and_trolls_client/models/dungeonsandtrolls_commands_batch.py
dungeons_and_trolls_client/models/dungeonsandtrolls_commands_for_monsters.py
dungeons_and_trolls_client/models/dungeonsandtrolls_coordinates.py
dungeons_and_trolls_client/models/dungeonsandtrolls_damage_type.py
dungeons_and_trolls_client/models/dungeonsandtrolls_decoration.py
dungeons_and_trolls_client/models/dungeonsandtrolls_droppable.py
dungeons_and_trolls_client/models/dungeonsandtrolls_effect.py
dungeons_and_trolls_client/models/dungeonsandtrolls_event.py
dungeons_and_trolls_client/models/dungeonsandtrolls_event_type.py
dungeons_and_trolls_client/models/dungeonsandtrolls_fog_of_war_map.py
dungeons_and_trolls_client/models/dungeonsandtrolls_game_state.py
dungeons_and_trolls_client/models/dungeonsandtrolls_identifier.py
dungeons_and_trolls_client/models/dungeonsandtrolls_identifiers.py
dungeons_and_trolls_client/models/dungeonsandtrolls_item.py
dungeons_and_trolls_client/models/dungeonsandtrolls_item_type.py
dungeons_and_trolls_client/models/dungeonsandtrolls_key.py
dungeons_and_trolls_client/models/dungeonsandtrolls_level.py
dungeons_and_trolls_client/models/dungeonsandtrolls_map.py
dungeons_and_trolls_client/models/dungeonsandtrolls_map_objects.py
dungeons_and_trolls_client/models/dungeonsandtrolls_message.py
dungeons_and_trolls_client/models/dungeonsandtrolls_monster.py
dungeons_and_trolls_client-1.10.0.dist-info/METADATA
dungeons_and_trolls_client-1.10.0.dist-info/WHEEL
dungeons_and_trolls_client-1.10.0.dist-info/top_level.txt
dungeons_and_trolls_client-1.10.0.dist-info/RECORD
