Metadata-Version: 2.1
Name: dungeons-and-trolls-client
Version: 1.10.0
Summary: Dungeons and Trolls
Home-page: 
Author: OpenAPI Generator community
Author-email: team@openapitools.org
Keywords: OpenAPI,OpenAPI-Generator,Dungeons and Trolls
Requires-Dist: urllib3 <2.1.0,>=1.25.3
Requires-Dist: python-dateutil
Requires-Dist: pydantic <2,>=1.10.5
Requires-Dist: aenum
